hivemind_core/__init__.py
hivemind_core/__main__.py
hivemind_core/database.py
hivemind_core/protocol.py
hivemind_core/scripts.py
hivemind_core/service.py
hivemind_core/version.py
jarbas_hive_mind-0.14.1.dist-info/LICENSE
jarbas_hive_mind-0.14.1.dist-info/METADATA
jarbas_hive_mind-0.14.1.dist-info/WHEEL
jarbas_hive_mind-0.14.1.dist-info/entry_points.txt
jarbas_hive_mind-0.14.1.dist-info/top_level.txt
jarbas_hive_mind-0.14.1.dist-info/RECORD
