Metadata-Version: 2.1
Name: jarbas-hive-mind
Version: 0.14.1
Summary: Mesh Networking utilities for OpenVoiceOS
Home-page: https://github.com/JarbasHiveMind/HiveMind-core
Author: jarbasAI
Author-email: jarbasai@mailfence.com
License: Apache2.0
Platform: UNKNOWN
Requires-Dist: tornado
Requires-Dist: click
Requires-Dist: click-default-group
Requires-Dist: rich
Requires-Dist: pyOpenSSL
Requires-Dist: pycryptodomex
Requires-Dist: poorman-handshake>=0.1.0
Requires-Dist: hivemind-ggwave
Requires-Dist: hivemind-bus-client<1.0.0,>=0.1.0
Requires-Dist: HiveMind-presence<1.0.0,>=0.0.2a3
Requires-Dist: ovos-utils<1.0.0,>=0.0.33
Requires-Dist: ovos-bus-client<2.0.0,>=0.0.6
